get_video_len/LICENSE
get_video_len/README.MD
get_video_len/__init__.py
get_video_len/requirements.txt
get_video_len/thirdparty.json
get_video_len-0.11.dist-info/LICENSE.rst
get_video_len-0.11.dist-info/METADATA
get_video_len-0.11.dist-info/WHEEL
get_video_len-0.11.dist-info/top_level.txt
get_video_len-0.11.dist-info/RECORD
